mooseherder/__init__.py
mooseherder/directorymanager.py
mooseherder/exodusreader.py
mooseherder/gmshrunner.py
mooseherder/inputmodifier.py
mooseherder/mooseconfig.py
mooseherder/mooseherd.py
mooseherder/mooserunner.py
mooseherder/outputreader.py
mooseherder/simdata.py
mooseherder/simrunner.py
mooseherder/sweepreader.py
mooseherder-2025.5.0.dist-info/licenses/LICENSE
mooseherder-2025.5.0.dist-info/METADATA
mooseherder-2025.5.0.dist-info/WHEEL
mooseherder-2025.5.0.dist-info/top_level.txt
mooseherder-2025.5.0.dist-info/RECORD
