Metadata-Version: 2.4
Name: mooseherder
Version: 2025.5.0
Summary: A herder for calling MOOSE and gmsh to run parallel parametric sweeps of multi-physics simulations.
Author-email: thescepticalrabbit <thescepticalrabbit@gmail.com>, fusmatrs <rory.spencer@ukaea.uk>, lukethehuman <luke.humphrey@ukaea.uk>
License:                   GNU LESSER GENERAL PUBLIC LICENSE
Project-URL: Repository, https://github.com/Computer-Aided-Validation-Laboratory/mooseherder
Project-URL: Issue Tracker, https://github.com/Computer-Aided-Validation-Laboratory/mooseherder/issues
Requires-Python: >=3.11
License-File: LICENSE
Requires-Dist: numpy<2.0.0
Requires-Dist: netCDF4>=1.6.5
Dynamic: license-file
